gmeet_shared_models/__init__.py
gmeet_shared_models/commands/__init__.py
gmeet_shared_models/commands/base/__init__.py
gmeet_shared_models/commands/base/command.py
gmeet_shared_models/commands/base/type.py
gmeet_shared_models/commands/join_meet.py
gmeet_shared_models/commands/leave_meet.py
gmeet_shared_models/commands/login_google_account.py
gmeet_shared_models/commands/publish_recording.py
gmeet_shared_models/commands/start_recording.py
gmeet_shared_models/commands/stop_recording.py
gmeet_shared_models/error/__init__.py
gmeet_shared_models/logs/__init__.py
gmeet_shared_models/py.typed
gmeet_shared_models/state/__init__.py
gmeet_shared_models-1.6.0.dist-info/METADATA
gmeet_shared_models-1.6.0.dist-info/WHEEL
gmeet_shared_models-1.6.0.dist-info/RECORD
