Metadata-Version: 2.3
Name: gmeet-shared-models
Version: 1.6.0
Summary: Pydantic models for communicate between gmeet bots and gmeet bot manager
Author: Ycalk
Author-email: 118367882+Ycalk@users.noreply.github.com
Requires-Python: >=3.11
Classifier: Programming Language :: Python :: 3
Classifier: Programming Language :: Python :: 3.11
Classifier: Programming Language :: Python :: 3.12
Classifier: Programming Language :: Python :: 3.13
Requires-Dist: pydantic (>=2.11.7,<3.0.0)
